a3mcat/__init__.py
a3mcat/examples.py
a3mcat/backend/__init__.py
a3mcat/backend/a3m_tools.py
a3mcat/backend/fasta_tools.py
a3mcat/backend/sequence_utils.py
a3mcat/test_data/__init__.py
a3mcat/test_data/test_msa_1.a3m
a3mcat/test_data/test_msa_2.a3m
a3mcat/test_data/test_msa_3.fasta
a3mcat/tests/__init__.py
a3mcat/tests/test_a3mtools.py
a3mcat-0.1.0a5.dist-info/licenses/LICENSE
a3mcat-0.1.0a5.dist-info/WHEEL
a3mcat-0.1.0a5.dist-info/METADATA
a3mcat-0.1.0a5.dist-info/RECORD
